{
  "order": [
    {
      "sno": "O455",
      "buyername": "fghfgj",
      "shippingaddress": "dfg",
      "city": "dfgd",
      "amount": 90,
      "contact": "8",
      "id": 2
    },
    {
      "sno": "O827",
      "buyername": "hhguugutgtuitfdgg",
      "shippingaddress": "etyeyteyte",
      "city": "tyertyrt",
      "amount": 4710,
      "contact": "5",
      "id": 6
    },
    {
      "sno": "O382",
      "buyername": "hkkjlkhljk",
      "shippingaddress": "khkhkj",
      "city": "hkhhk",
      "amount": 112,
      "contact": "3667777777",
      "id": 7
    },
    {
      "sno": "O272",
      "buyername": "hkkjlkhljk",
      "shippingaddress": "khkhkj",
      "city": "hkhhk",
      "amount": 112,
      "contact": "7667777777",
      "id": 8
    },
    {
      "sno": "O203",
      "buyername": "hkkjlkhljk",
      "shippingaddress": "khkhkj",
      "city": "hkhhk",
      "amount": 112,
      "contact": "7667777777",
      "id": 9
    },
    {
      "sno": "O382",
      "buyername": "",
      "shippingaddress": "",
      "city": "",
      "amount": "",
      "contact": "",
      "id": 10
    }
  ]
}